proctap_pipes/__init__.py
proctap_pipes/base.py
proctap_pipes/llm_pipe.py
proctap_pipes/volume_meter_pipe.py
proctap_pipes/webhook_pipe.py
proctap_pipes/whisper_pipe.py
proctap_pipes/cli/__init__.py
proctap_pipes/cli/llm_cli.py
proctap_pipes/cli/volume_meter_cli.py
proctap_pipes/cli/webhook_cli.py
proctap_pipes/cli/whisper_cli.py
proctap_pipes-0.1.1.dist-info/licenses/LICENSE
proctap_pipes-0.1.1.dist-info/METADATA
proctap_pipes-0.1.1.dist-info/WHEEL
proctap_pipes-0.1.1.dist-info/entry_points.txt
proctap_pipes-0.1.1.dist-info/top_level.txt
proctap_pipes-0.1.1.dist-info/RECORD
