Metadata-Version: 2.4
Name: proctap-pipes
Version: 0.1.1
Summary: Official companion toolkit for ProcTap - modular audio-processing utilities for real-time workflows
Author: ProcTap Contributors
License: MIT
Project-URL: Homepage, https://github.com/proctap/proctap-pipes
Project-URL: Documentation, https://github.com/proctap/proctap-pipes#readme
Project-URL: Repository, https://github.com/proctap/proctap-pipes
Project-URL: Issues, https://github.com/proctap/proctap-pipes/issues
Keywords: audio,processing,proctap,whisper,transcription,streaming
Classifier: Development Status :: 3 - Alpha
Classifier: Intended Audience :: Developers
Classifier: License :: OSI Approved :: MIT License
Classifier: Programming Language :: Python :: 3
Classifier: Programming Language :: Python :: 3.10
Classifier: Programming Language :: Python :: 3.11
Classifier: Programming Language :: Python :: 3.12
Classifier: Topic :: Multimedia :: Sound/Audio :: Capture/Recording
Classifier: Topic :: Software Development :: Libraries :: Python Modules
Requires-Python: >=3.10
License-File: LICENSE
Requires-Dist: numpy>=1.24.0
Requires-Dist: click>=8.1.0
Requires-Dist: requests>=2.31.0
Requires-Dist: openai>=1.0.0
Provides-Extra: dev
Requires-Dist: pytest>=7.4.0; extra == "dev"
Requires-Dist: pytest-cov>=4.1.0; extra == "dev"
Requires-Dist: black>=23.0.0; extra == "dev"
Requires-Dist: ruff>=0.1.0; extra == "dev"
Requires-Dist: mypy>=1.5.0; extra == "dev"
Provides-Extra: whisper
Requires-Dist: faster-whisper>=1.0.0; extra == "whisper"
Provides-Extra: whisper-openai
Requires-Dist: openai>=1.0.0; extra == "whisper-openai"
Provides-Extra: all
Requires-Dist: proctap-pipes[whisper,whisper-openai]; extra == "all"
Dynamic: license-file
